quickspec/__init__.py
quickspec/main.py
quickspec-0.1.0.dist-info/licenses/LICENSE
quickspec-0.1.0.dist-info/METADATA
quickspec-0.1.0.dist-info/WHEEL
quickspec-0.1.0.dist-info/entry_points.txt
quickspec-0.1.0.dist-info/top_level.txt
quickspec-0.1.0.dist-info/RECORD
